spwm/__init__.py
spwm/plugin.py
spwm-0.1.5.dist-info/AUTHORS.rst
spwm-0.1.5.dist-info/LICENSE
spwm-0.1.5.dist-info/METADATA
spwm-0.1.5.dist-info/WHEEL
spwm-0.1.5.dist-info/entry_points.txt
spwm-0.1.5.dist-info/top_level.txt
spwm-0.1.5.dist-info/RECORD
