Metadata-Version: 2.1
Name: spwm
Version: 0.1.5
Summary: Saleor Plugin for Wechat Miniprogram
Home-page: https://github.com/riiy/spwm
Author: riiy
Author-email: riiy.zhou@gmail.com
License: GNU General Public License v3
Keywords: spwm
Platform: UNKNOWN
Classifier: Development Status :: 2 - Pre-Alpha
Classifier: Intended Audience :: Developers
Classifier: License :: OSI Approved :: GNU General Public License v3 (GPLv3)
Classifier: Natural Language :: English
Classifier: Programming Language :: Python :: 3
Classifier: Programming Language :: Python :: 3.6
Classifier: Programming Language :: Python :: 3.7
Classifier: Programming Language :: Python :: 3.8
Requires-Python: >=3.6
